{
  "collapse-filter": false,
  "search": "",
  "showTags": true,
  "showAttachments": true,
  "hideUnresolved": true,
  "showOrphans": false,
  "collapse-color-groups": true,
  "colorGroups": [
    {
      "query": "path:\"Media DB\"  ",
      "color": {
        "a": 1,
        "rgb": 786611
      }
    },
    {
      "query": "path:thesis  ",
      "color": {
        "a": 1,
        "rgb": 16711731
      }
    },
    {
      "query": "path:research  ",
      "color": {
        "a": 1,
        "rgb": 16741120
      }
    },
    {
      "query": "path:zotero  ",
      "color": {
        "a": 1,
        "rgb": 16711680
      }
    },
    {
      "query": "path:utils  ",
      "color": {
        "a": 1,
        "rgb": 1184274
      }
    }
  ],
  "collapse-display": false,
  "showArrow": true,
  "textFadeMultiplier": -1.3,
  "nodeSizeMultiplier": 1,
  "lineSizeMultiplier": 1,
  "collapse-forces": true,
  "centerStrength": 0.572916666666667,
  "repelStrength": 13.125,
  "linkStrength": 0.807291666666667,
  "linkDistance": 138,
  "scale": 0.13821237443079606,
  "close": false
}